o_re/__init__.py
o_re/base.py
o_re/conditional.py
o_re/construction.py
o_re/groups.py
o_re/ops.py
o_re/options.py
o_re/repeats.py
o_re/symbols.py
o_re/text.py
o_re/tools.py
o_re/types.py
objective_regex-0.1.4.dist-info/LICENSE
objective_regex-0.1.4.dist-info/METADATA
objective_regex-0.1.4.dist-info/WHEEL
objective_regex-0.1.4.dist-info/top_level.txt
objective_regex-0.1.4.dist-info/RECORD
