Metadata-Version: 2.1
Name: objective-regex
Version: 0.1.4
Summary: Objective regular expressions
Home-page: https://github.com/VRGhost/objective_regex
Author: Ilja Orlovs
Author-email: vrghost@gmail.com
License: UNKNOWN
Project-URL: Bug Tracker, https://github.com/VRGhost/objective_regex/issues
Platform: UNKNOWN
Classifier: Programming Language :: Python :: 3
Classifier: License :: OSI Approved :: MIT License
Classifier: Operating System :: OS Independent
Requires-Python: >=3.6
License-File: LICENSE
